djangocms_bootstrap4/__init__.py
djangocms_bootstrap4/constants.py
djangocms_bootstrap4/fields.py
djangocms_bootstrap4/helpers.py
djangocms_bootstrap4/contrib/__init__.py
djangocms_bootstrap4/contrib/bootstrap4_alerts/__init__.py
djangocms_bootstrap4/contrib/bootstrap4_alerts/cms_plugins.py
djangocms_bootstrap4/contrib/bootstrap4_alerts/models.py
djangocms_bootstrap4/contrib/bootstrap4_alerts/migrations/0001_initial.py
djangocms_bootstrap4/contrib/bootstrap4_alerts/migrations/__init__.py
djangocms_bootstrap4/contrib/bootstrap4_alerts/templates/djangocms_bootstrap4/alerts.html
djangocms_bootstrap4/contrib/bootstrap4_alerts/templates/djangocms_bootstrap4/admin/alerts.html
djangocms_bootstrap4/contrib/bootstrap4_badge/__init__.py
djangocms_bootstrap4/contrib/bootstrap4_badge/cms_plugins.py
djangocms_bootstrap4/contrib/bootstrap4_badge/models.py
djangocms_bootstrap4/contrib/bootstrap4_badge/migrations/0001_initial.py
djangocms_bootstrap4/contrib/bootstrap4_badge/migrations/__init__.py
djangocms_bootstrap4/contrib/bootstrap4_badge/templates/djangocms_bootstrap4/badge.html
djangocms_bootstrap4/contrib/bootstrap4_badge/templates/djangocms_bootstrap4/admin/badge.html
djangocms_bootstrap4/contrib/bootstrap4_card/__init__.py
djangocms_bootstrap4/contrib/bootstrap4_card/cms_plugins.py
djangocms_bootstrap4/contrib/bootstrap4_card/constants.py
djangocms_bootstrap4/contrib/bootstrap4_card/models.py
djangocms_bootstrap4/contrib/bootstrap4_card/migrations/0001_initial.py
djangocms_bootstrap4/contrib/bootstrap4_card/migrations/__init__.py
djangocms_bootstrap4/contrib/bootstrap4_card/templates/djangocms_bootstrap4/card.html
djangocms_bootstrap4/contrib/bootstrap4_card/templates/djangocms_bootstrap4/card_content.html
djangocms_bootstrap4/contrib/bootstrap4_card/templates/djangocms_bootstrap4/admin/card.html
djangocms_bootstrap4/contrib/bootstrap4_carousel/__init__.py
djangocms_bootstrap4/contrib/bootstrap4_carousel/cms_plugins.py
djangocms_bootstrap4-3.0.2.dist-info/LICENSE
djangocms_bootstrap4-3.0.2.dist-info/METADATA
djangocms_bootstrap4-3.0.2.dist-info/WHEEL
djangocms_bootstrap4-3.0.2.dist-info/top_level.txt
djangocms_bootstrap4-3.0.2.dist-info/RECORD
