Metadata-Version: 2.1
Name: djangocms-bootstrap4
Version: 3.0.2
Summary: Adds Bootstrap 4 components as plugins.
Home-page: https://github.com/django-cms/djangocms-bootstrap4
Author: Divio AG
Author-email: info@divio.ch
Maintainer: Django CMS Association and contributors
Maintainer-email: info@django-cms.org
License: BSD-3-Clause
Classifier: Development Status :: 5 - Production/Stable
Classifier: Environment :: Web Environment
Classifier: Intended Audience :: Developers
Classifier: License :: OSI Approved :: BSD License
Classifier: Operating System :: OS Independent
Classifier: Programming Language :: Python
Classifier: Programming Language :: Python :: 3
Classifier: Programming Language :: Python :: 3.10
Classifier: Programming Language :: Python :: 3.11
Classifier: Programming Language :: Python :: 3.12
Classifier: Framework :: Django
Classifier: Framework :: Django :: 3.2
Classifier: Framework :: Django :: 4.2
Classifier: Framework :: Django CMS
Classifier: Framework :: Django CMS :: 3.7
Classifier: Framework :: Django CMS :: 3.8
Classifier: Framework :: Django CMS :: 3.9
Classifier: Framework :: Django CMS :: 3.10
Classifier: Topic :: Internet :: WWW/HTTP
Classifier: Topic :: Internet :: WWW/HTTP :: Dynamic Content
Classifier: Topic :: Software Development
Classifier: Topic :: Software Development :: Libraries
License-File: LICENSE
Requires-Dist: django-cms <4,>=3.7
Requires-Dist: django-filer >=1.7
Requires-Dist: djangocms-attributes-field >=1
Requires-Dist: djangocms-text-ckeditor >=3.1.0
Requires-Dist: djangocms-icon >=1.4.0
Requires-Dist: djangocms-link >=2.5.0
Requires-Dist: djangocms-picture >=2.3.0
Provides-Extra: static-ace
Requires-Dist: djangocms-static-ace ; extra == 'static-ace'
